smtprelayapi/__init__.py
smtprelayapi/__main__.py
smtprelayapi/client.py
smtprelayapi/logging.py
smtprelayapi-1.0.0.dist-info/LICENSE
smtprelayapi-1.0.0.dist-info/METADATA
smtprelayapi-1.0.0.dist-info/WHEEL
smtprelayapi-1.0.0.dist-info/entry_points.txt
smtprelayapi-1.0.0.dist-info/top_level.txt
smtprelayapi-1.0.0.dist-info/RECORD
