Metadata-Version: 2.1
Name: smtprelayapi
Version: 1.0.0
Summary: API for connecting to the smtprelay server.
Home-page: https://github.com/dfo-meds/smtp-relay-client
Author: Erin Turnbull
Author-email: erin.a.turnbull@gmail.com
Project-URL: Bug Tracker, https://github.com/dfo-meds/smtp-relay-client/issues
Classifier: Programming Language :: Python :: 3
Classifier: License :: OSI Approved :: MIT License
Classifier: Operating System :: OS Independent
Requires-Python: >=3.7
License-File: LICENSE
Requires-Dist: requests
Requires-Dist: zirconium (>=0.2.2)
Requires-Dist: autoinject (>=1.0.1)
